onesaitplatform_client_services-1.4.18-py3.11-nspkg.pth
onesaitplatform/apimanager/__init__.py
onesaitplatform/apimanager/apimanagerclient.py
onesaitplatform/base/__init__.py
onesaitplatform/base/client.py
onesaitplatform/common/__init__.py
onesaitplatform/common/config.py
onesaitplatform/common/log.py
onesaitplatform/common/utils.py
onesaitplatform/enum/__init__.py
onesaitplatform/enum/querytype.py
onesaitplatform/enum/resprotocols.py
onesaitplatform/enum/restheaders.py
onesaitplatform/enum/restmethods.py
onesaitplatform/files/__init__.py
onesaitplatform/files/filemanager.py
onesaitplatform/files/filemanager_test.py
onesaitplatform/iotbroker/__init__.py
onesaitplatform/iotbroker/digitalclient.py
onesaitplatform/iotbroker/digitalclient_test.py
onesaitplatform/microservice/__init__.py
onesaitplatform/microservice/modelserviceclient.py
onesaitplatform/mqttclient/__init__.py
onesaitplatform/mqttclient/core.py
onesaitplatform/mqttclient/utils.py
onesaitplatform_client_services-1.4.18.dist-info/licenses/LICENSE
onesaitplatform_client_services-1.4.18.dist-info/METADATA
onesaitplatform_client_services-1.4.18.dist-info/WHEEL
onesaitplatform_client_services-1.4.18.dist-info/namespace_packages.txt
onesaitplatform_client_services-1.4.18.dist-info/top_level.txt
onesaitplatform_client_services-1.4.18.dist-info/RECORD
