Metadata-Version: 2.4
Name: onesaitplatform-client-services
Version: 1.4.18
Summary: Python Implementation of the Onesait Platform utilities
Home-page: 
License: Apache v2.0
Keywords: onesaitplatform client services
License-File: LICENSE
Requires-Dist: paho-mqtt
Requires-Dist: six
Requires-Dist: requests
Dynamic: description
Dynamic: description-content-type
Dynamic: keywords
Dynamic: license
Dynamic: license-file
Dynamic: requires-dist
Dynamic: summary
